LICENSE
README.md
setup.py
src/pyhole/AstWalker.py
src/pyhole/HoleAST.py
src/pyhole/Matcher.py
src/pyhole/PatternMatch.py
src/pyhole/PyHoleErrorListener.py
src/pyhole/PyHoleParser.py
src/pyhole/PyHoleVisitor.py
src/pyhole/__init__.py
src/pyhole/antlr/Python3Lexer.py
src/pyhole/antlr/Python3Listener.py
src/pyhole/antlr/Python3Parser.py
src/pyhole/antlr/Python3Visitor.py
src/pyhole/antlr/__init__.py
src/pyhole/visualizer/Visualizer.py
src/pyhole/visualizer/__init__.py
src/python_hole.egg-info/PKG-INFO
src/python_hole.egg-info/SOURCES.txt
src/python_hole.egg-info/dependency_links.txt
src/python_hole.egg-info/requires.txt
src/python_hole.egg-info/top_level.txt