Metadata-Version: 2.1
Name: python-hole
Version: 0.0.9
Summary: Python package to build code patterns
Home-page: https://github.com/JulienLie/python-hole
Author: Julien Lienard
Author-email: julien.lienard@uclouvain.be
License: MIT
Platform: UNKNOWN
